plonetheme.business_casual-1.0a1-py2.7-nspkg.pth
plonetheme/business_casual/__init__.py
plonetheme/business_casual/configure.zcml
plonetheme/business_casual/interfaces.py
plonetheme/business_casual/setuphandlers.py
plonetheme/business_casual/testing.py
plonetheme/business_casual/browser/__init__.py
plonetheme/business_casual/browser/configure.zcml
plonetheme/business_casual/browser/overrides/.gitkeep
plonetheme/business_casual/browser/static/.gitkeep
plonetheme/business_casual/locales/plonetheme.business_casual.pot
plonetheme/business_casual/locales/update.sh
plonetheme/business_casual/profiles/default/browserlayer.xml
plonetheme/business_casual/profiles/default/metadata.xml
plonetheme/business_casual/profiles/default/theme.xml
plonetheme/business_casual/profiles/uninstall/browserlayer.xml
plonetheme/business_casual/profiles/uninstall/theme.xml
plonetheme/business_casual/tests/__init__.py
plonetheme/business_casual/tests/test_robot.py
plonetheme/business_casual/tests/test_setup.py
plonetheme/business_casual/tests/robot/test_example.robot
plonetheme/business_casual/theme/LICENSE
plonetheme/business_casual/theme/README.md
plonetheme/business_casual/theme/index.html
plonetheme/business_casual/theme/manifest.cfg
plonetheme/business_casual/theme/preview.png
plonetheme/business_casual/theme/rules.xml
plonetheme/business_casual/theme/fonts/glyphicons-halflings-regular.eot
plonetheme/business_casual/theme/fonts/glyphicons-halflings-regular.svg
plonetheme/business_casual/theme/fonts/glyphicons-halflings-regular.ttf
plonetheme/business_casual/theme/fonts/glyphicons-halflings-regular.woff
plonetheme/business_casual/theme/fonts/glyphicons-halflings-regular.woff2
plonetheme/business_casual/theme/images/bg.jpg
plonetheme/business_casual/theme/images/slide-1.jpg
plonetheme/business_casual/theme/less/bootstrap.min.css
plonetheme/business_casual/theme/less/business-casual-compiled.css.map
plonetheme/business_casual/theme/less/business-casual.css
plonetheme.business_casual-1.0a1.dist-info/DESCRIPTION.rst
plonetheme.business_casual-1.0a1.dist-info/METADATA
plonetheme.business_casual-1.0a1.dist-info/RECORD
plonetheme.business_casual-1.0a1.dist-info/WHEEL
plonetheme.business_casual-1.0a1.dist-info/entry_points.txt
plonetheme.business_casual-1.0a1.dist-info/metadata.json
plonetheme.business_casual-1.0a1.dist-info/namespace_packages.txt
plonetheme.business_casual-1.0a1.dist-info/top_level.txt
